vedadb/__init__.py
vedadb/connexion.py
vedadb/dimensionContent.py
vedadb/endpoint.py
vedadb/entete.py
vedadb/fileToDataframe.py
vedadb/resultat.py
vedadb/sets.py
vedadb/tableCreated.py
vedadb-0.2.5.dist-info/METADATA
vedadb-0.2.5.dist-info/WHEEL
vedadb-0.2.5.dist-info/top_level.txt
vedadb-0.2.5.dist-info/RECORD
